email_tools/__init__.py
email_tools/apps.py
email_tools/emails.py
email_tools/settings.py
email_tools/urls.py
email_tools/views.py
email_tools/templates/email_preview.html
django_email_tools-0.1.1.dist-info/LICENSE
django_email_tools-0.1.1.dist-info/METADATA
django_email_tools-0.1.1.dist-info/WHEEL
django_email_tools-0.1.1.dist-info/top_level.txt
django_email_tools-0.1.1.dist-info/RECORD
